ok_subprocess_defaults.py
ok_subprocess_defaults-0.1.dist-info/METADATA
ok_subprocess_defaults-0.1.dist-info/WHEEL
ok_subprocess_defaults-0.1.dist-info/licenses/LICENSE
ok_subprocess_defaults-0.1.dist-info/RECORD
