Metadata-Version: 2.4
Name: ok-subprocess-defaults
Version: 0.1
Summary: Minor wrapper for subprocess.run() with defaults and logging
Project-URL: Homepage, https://github.com/egnor/ok-py-subprocess-defaults#readme
Project-URL: Repository, https://github.com/egnor/ok-py-subprocess-defaults.git
Author-email: Dan Egnor <egnor@ofb.net>
License-File: LICENSE
Requires-Python: >=3.9
Provides-Extra: dev
Requires-Dist: pytest; extra == 'dev'
